{
  "id": "feb88489-2139-4a5b-8dfa-d201ed7f7c89",
  "prevId": "ab406704-22a9-4fb1-bf33-e47702b9678b",
  "version": "7",
  "dialect": "postgresql",
  "tables": {
    "better-auth.account": {
      "name": "account",
      "schema": "better-auth",
      "columns": {
        "id": {
          "name": "id",
          "type": "uuid",
          "primaryKey": true,
          "notNull": true,
          "default": "uuid_generate_v7()"
        },
        "account_id": {
          "name": "account_id",
          "type": "text",
          "primaryKey": false,
          "notNull": true
        },
        "provider_id": {
          "name": "provider_id",
          "type": "text",
          "primaryKey": false,
          "notNull": true
        },
        "user_id": {
          "name": "user_id",
          "type": "text",
          "primaryKey": false,
          "notNull": true
        },
        "access_token": {
          "name": "access_token",
          "type": "text",
          "primaryKey": false,
          "notNull": false
        },
        "refresh_token": {
          "name": "refresh_token",
          "type": "text",
          "primaryKey": false,
          "notNull": false
        },
        "id_token": {
          "name": "id_token",
          "type": "text",
          "primaryKey": false,
          "notNull": false
        },
        "access_token_expires_at": {
          "name": "access_token_expires_at",
          "type": "timestamp",
          "primaryKey": false,
          "notNull": false
        },
        "refresh_token_expires_at": {
          "name": "refresh_token_expires_at",
          "type": "timestamp",
          "primaryKey": false,
          "notNull": false
        },
        "scope": {
          "name": "scope",
          "type": "text",
          "primaryKey": false,
          "notNull": false
        },
        "password": {
          "name": "password",
          "type": "text",
          "primaryKey": false,
          "notNull": false
        },
        "created_at": {
          "name": "created_at",
          "type": "timestamp",
          "primaryKey": false,
          "notNull": true,
          "default": "now()"
        },
        "updated_at": {
          "name": "updated_at",
          "type": "timestamp",
          "primaryKey": false,
          "notNull": true
        }
      },
      "indexes": {},
      "foreignKeys": {},
      "compositePrimaryKeys": {},
      "uniqueConstraints": {},
      "policies": {},
      "checkConstraints": {},
      "isRLSEnabled": false
    },
    "authz.certifications": {
      "name": "certifications",
      "schema": "authz",
      "columns": {
        "id": {
          "name": "id",
          "type": "uuid",
          "primaryKey": true,
          "notNull": true,
          "default": "uuid_generate_v7()"
        },
        "name": {
          "name": "name",
          "type": "text",
          "primaryKey": false,
          "notNull": true
        },
        "display": {
          "name": "display",
          "type": "text",
          "primaryKey": false,
          "notNull": true
        }
      },
      "indexes": {},
      "foreignKeys": {},
      "compositePrimaryKeys": {},
      "uniqueConstraints": {
        "certifications_name_key": {
          "name": "certifications_name_key",
          "nullsNotDistinct": false,
          "columns": [
            "name"
          ]
        }
      },
      "policies": {},
      "checkConstraints": {},
      "isRLSEnabled": false
    },
    "calendar.events": {
      "name": "events",
      "schema": "calendar",
      "columns": {
        "id": {
          "name": "id",
          "type": "uuid",
          "primaryKey": true,
          "notNull": true,
          "default": "uuid_generate_v7()"
        },
        "name": {
          "name": "name",
          "type": "text",
          "primaryKey": false,
          "notNull": true
        },
        "description": {
          "name": "description",
          "type": "text",
          "primaryKey": false,
          "notNull": false
        },
        "location": {
          "name": "location",
          "type": "text",
          "primaryKey": false,
          "notNull": false
        },
        "time_begin": {
          "name": "time_begin",
          "type": "timestamp with time zone",
          "primaryKey": false,
          "notNull": false
        },
        "time_end": {
          "name": "time_end",
          "type": "timestamp with time zone",
          "primaryKey": false,
          "notNull": false
        },
        "created_by": {
          "name": "created_by",
          "type": "uuid",
          "primaryKey": false,
          "notNull": false
        }
      },
      "indexes": {},
      "foreignKeys": {
        "created_by": {
          "name": "created_by",
          "tableFrom": "events",
          "tableTo": "user",
          "schemaTo": "better-auth",
          "columnsFrom": [
            "created_by"
          ],
          "columnsTo": [
            "id"
          ],
          "onDelete": "no action",
          "onUpdate": "cascade"
        }
      },
      "compositePrimaryKeys": {},
      "uniqueConstraints": {},
      "policies": {},
      "checkConstraints": {},
      "isRLSEnabled": false
    },
    "calendar.junction_shifts": {
      "name": "junction_shifts",
      "schema": "calendar",
      "columns": {
        "id": {
          "name": "id",
          "type": "uuid",
          "primaryKey": true,
          "notNull": true,
          "default": "uuid_generate_v7()"
        },
        "event_id": {
          "name": "event_id",
          "type": "uuid",
          "primaryKey": false,
          "notNull": true
        },
        "position_id": {
          "name": "position_id",
          "type": "uuid",
          "primaryKey": false,
          "notNull": true
        },
        "quantity": {
          "name": "quantity",
          "type": "integer",
          "primaryKey": false,
          "notNull": true,
          "default": 1
        },
        "status": {
          "name": "status",
          "type": "shift_status",
          "typeSchema": "public",
          "primaryKey": false,
          "notNull": false,
          "default": "'active'"
        }
      },
      "indexes": {},
      "foreignKeys": {
        "event_id": {
          "name": "event_id",
          "tableFrom": "junction_shifts",
          "tableTo": "events",
          "schemaTo": "calendar",
          "columnsFrom": [
            "event_id"
          ],
          "columnsTo": [
            "id"
          ],
          "onDelete": "cascade",
          "onUpdate": "cascade"
        },
        "position_id": {
          "name": "position_id",
          "tableFrom": "junction_shifts",
          "tableTo": "positions",
          "schemaTo": "calendar",
          "columnsFrom": [
            "position_id"
          ],
          "columnsTo": [
            "id"
          ],
          "onDelete": "cascade",
          "onUpdate": "cascade"
        }
      },
      "compositePrimaryKeys": {},
      "uniqueConstraints": {},
      "policies": {},
      "checkConstraints": {},
      "isRLSEnabled": false
    },
    "calendar.junction_slots": {
      "name": "junction_slots",
      "schema": "calendar",
      "columns": {
        "id": {
          "name": "id",
          "type": "uuid",
          "primaryKey": true,
          "notNull": true,
          "default": "uuid_generate_v7()"
        },
        "shift_id": {
          "name": "shift_id",
          "type": "uuid",
          "primaryKey": false,
          "notNull": true
        },
        "user_id": {
          "name": "user_id",
          "type": "uuid",
          "primaryKey": false,
          "notNull": true
        },
        "status": {
          "name": "status",
          "type": "slot_status",
          "typeSchema": "public",
          "primaryKey": false,
          "notNull": false,
          "default": "'active'"
        }
      },
      "indexes": {},
      "foreignKeys": {
        "shift_id": {
          "name": "shift_id",
          "tableFrom": "junction_slots",
          "tableTo": "junction_shifts",
          "schemaTo": "calendar",
          "columnsFrom": [
            "shift_id"
          ],
          "columnsTo": [
            "id"
          ],
          "onDelete": "cascade",
          "onUpdate": "cascade"
        },
        "user_id": {
          "name": "user_id",
          "tableFrom": "junction_slots",
          "tableTo": "user",
          "schemaTo": "better-auth",
          "columnsFrom": [
            "user_id"
          ],
          "columnsTo": [
            "id"
          ],
          "onDelete": "set null",
          "onUpdate": "cascade"
        }
      },
      "compositePrimaryKeys": {},
      "uniqueConstraints": {},
      "policies": {},
      "checkConstraints": {},
      "isRLSEnabled": false
    },
    "calendar.junction_template_positions": {
      "name": "junction_template_positions",
      "schema": "calendar",
      "columns": {
        "id": {
          "name": "id",
          "type": "uuid",
          "primaryKey": true,
          "notNull": true,
          "default": "uuid_generate_v7()"
        },
        "template_id": {
          "name": "template_id",
          "type": "uuid",
          "primaryKey": false,
          "notNull": true
        },
        "position_id": {
          "name": "position_id",
          "type": "uuid",
          "primaryKey": false,
          "notNull": true
        },
        "quantity": {
          "name": "quantity",
          "type": "integer",
          "primaryKey": false,
          "notNull": true,
          "default": 1
        }
      },
      "indexes": {},
      "foreignKeys": {
        "template_id_fkey": {
          "name": "template_id_fkey",
          "tableFrom": "junction_template_positions",
          "tableTo": "templates",
          "schemaTo": "calendar",
          "columnsFrom": [
            "template_id"
          ],
          "columnsTo": [
            "id"
          ],
          "onDelete": "no action",
          "onUpdate": "no action"
        },
        "position_id_fkey": {
          "name": "position_id_fkey",
          "tableFrom": "junction_template_positions",
          "tableTo": "positions",
          "schemaTo": "calendar",
          "columnsFrom": [
            "position_id"
          ],
          "columnsTo": [
            "id"
          ],
          "onDelete": "no action",
          "onUpdate": "no action"
        }
      },
      "compositePrimaryKeys": {},
      "uniqueConstraints": {},
      "policies": {},
      "checkConstraints": {},
      "isRLSEnabled": false
    },
    "calendar.positions": {
      "name": "positions",
      "schema": "calendar",
      "columns": {
        "id": {
          "name": "id",
          "type": "uuid",
          "primaryKey": true,
          "notNull": true,
          "default": "uuid_generate_v7()"
        },
        "name": {
          "name": "name",
          "type": "text",
          "primaryKey": false,
          "notNull": true
        },
        "display": {
          "name": "display",
          "type": "text",
          "primaryKey": false,
          "notNull": true
        },
        "description": {
          "name": "description",
          "type": "text",
          "primaryKey": false,
          "notNull": false
        }
      },
      "indexes": {},
      "foreignKeys": {},
      "compositePrimaryKeys": {},
      "uniqueConstraints": {
        "positions_name_key": {
          "name": "positions_name_key",
          "nullsNotDistinct": false,
          "columns": [
            "name"
          ]
        }
      },
      "policies": {},
      "checkConstraints": {},
      "isRLSEnabled": false
    },
    "better-auth.session": {
      "name": "session",
      "schema": "better-auth",
      "columns": {
        "id": {
          "name": "id",
          "type": "uuid",
          "primaryKey": true,
          "notNull": true,
          "default": "uuid_generate_v7()"
        },
        "expires_at": {
          "name": "expires_at",
          "type": "timestamp",
          "primaryKey": false,
          "notNull": true
        },
        "token": {
          "name": "token",
          "type": "text",
          "primaryKey": false,
          "notNull": true
        },
        "created_at": {
          "name": "created_at",
          "type": "timestamp",
          "primaryKey": false,
          "notNull": true,
          "default": "now()"
        },
        "updated_at": {
          "name": "updated_at",
          "type": "timestamp",
          "primaryKey": false,
          "notNull": true
        },
        "ip_address": {
          "name": "ip_address",
          "type": "text",
          "primaryKey": false,
          "notNull": false
        },
        "user_agent": {
          "name": "user_agent",
          "type": "text",
          "primaryKey": false,
          "notNull": false
        },
        "user_id": {
          "name": "user_id",
          "type": "uuid",
          "primaryKey": false,
          "notNull": true
        },
        "impersonated_by": {
          "name": "impersonated_by",
          "type": "text",
          "primaryKey": false,
          "notNull": false
        }
      },
      "indexes": {},
      "foreignKeys": {
        "session_user_id_user_id_fk": {
          "name": "session_user_id_user_id_fk",
          "tableFrom": "session",
          "tableTo": "user",
          "schemaTo": "better-auth",
          "columnsFrom": [
            "user_id"
          ],
          "columnsTo": [
            "id"
          ],
          "onDelete": "cascade",
          "onUpdate": "no action"
        }
      },
      "compositePrimaryKeys": {},
      "uniqueConstraints": {
        "session_token_unique": {
          "name": "session_token_unique",
          "nullsNotDistinct": false,
          "columns": [
            "token"
          ]
        }
      },
      "policies": {},
      "checkConstraints": {},
      "isRLSEnabled": false
    },
    "authz.system_roles": {
      "name": "system_roles",
      "schema": "authz",
      "columns": {
        "id": {
          "name": "id",
          "type": "uuid",
          "primaryKey": true,
          "notNull": true,
          "default": "uuid_generate_v7()"
        },
        "name": {
          "name": "name",
          "type": "text",
          "primaryKey": false,
          "notNull": true
        },
        "display": {
          "name": "display",
          "type": "text",
          "primaryKey": false,
          "notNull": true
        }
      },
      "indexes": {},
      "foreignKeys": {},
      "compositePrimaryKeys": {},
      "uniqueConstraints": {
        "system_roles_name_key": {
          "name": "system_roles_name_key",
          "nullsNotDistinct": false,
          "columns": [
            "name"
          ]
        }
      },
      "policies": {},
      "checkConstraints": {},
      "isRLSEnabled": false
    },
    "calendar.templates": {
      "name": "templates",
      "schema": "calendar",
      "columns": {
        "id": {
          "name": "id",
          "type": "uuid",
          "primaryKey": true,
          "notNull": true,
          "default": "uuid_generate_v7()"
        },
        "name": {
          "name": "name",
          "type": "text",
          "primaryKey": false,
          "notNull": true
        },
        "display": {
          "name": "display",
          "type": "text",
          "primaryKey": false,
          "notNull": true
        },
        "description": {
          "name": "description",
          "type": "text",
          "primaryKey": false,
          "notNull": false
        },
        "time_begin": {
          "name": "time_begin",
          "type": "time",
          "primaryKey": false,
          "notNull": true
        },
        "time_end": {
          "name": "time_end",
          "type": "time",
          "primaryKey": false,
          "notNull": false
        },
        "location": {
          "name": "location",
          "type": "text",
          "primaryKey": false,
          "notNull": false
        }
      },
      "indexes": {},
      "foreignKeys": {},
      "compositePrimaryKeys": {},
      "uniqueConstraints": {
        "templates_name_key": {
          "name": "templates_name_key",
          "nullsNotDistinct": false,
          "columns": [
            "name"
          ]
        }
      },
      "policies": {},
      "checkConstraints": {},
      "isRLSEnabled": false
    },
    "better-auth.user": {
      "name": "user",
      "schema": "better-auth",
      "columns": {
        "id": {
          "name": "id",
          "type": "uuid",
          "primaryKey": true,
          "notNull": true,
          "default": "uuid_generate_v7()"
        },
        "display_name": {
          "name": "display_name",
          "type": "text",
          "primaryKey": false,
          "notNull": true
        },
        "email": {
          "name": "email",
          "type": "text",
          "primaryKey": false,
          "notNull": true
        },
        "email_verified": {
          "name": "email_verified",
          "type": "boolean",
          "primaryKey": false,
          "notNull": true,
          "default": false
        },
        "image": {
          "name": "image",
          "type": "text",
          "primaryKey": false,
          "notNull": false
        },
        "name_first": {
          "name": "name_first",
          "type": "text",
          "primaryKey": false,
          "notNull": false
        },
        "name_middle": {
          "name": "name_middle",
          "type": "text",
          "primaryKey": false,
          "notNull": false
        },
        "name_last": {
          "name": "name_last",
          "type": "text",
          "primaryKey": false,
          "notNull": false
        },
        "phone_number": {
          "name": "phone_number",
          "type": "text",
          "primaryKey": false,
          "notNull": false
        },
        "phone_number_verified": {
          "name": "phone_number_verified",
          "type": "boolean",
          "primaryKey": false,
          "notNull": false
        },
        "post_nominals": {
          "name": "post_nominals",
          "type": "text",
          "primaryKey": false,
          "notNull": false
        },
        "status": {
          "name": "status",
          "type": "account_status",
          "typeSchema": "public",
          "primaryKey": false,
          "notNull": false
        },
        "timestamp_created_at": {
          "name": "timestamp_created_at",
          "type": "timestamp",
          "primaryKey": false,
          "notNull": true,
          "default": "now()"
        },
        "timestamp_first_login": {
          "name": "timestamp_first_login",
          "type": "timestamp",
          "primaryKey": false,
          "notNull": false
        },
        "timestamp_onboarding_completed": {
          "name": "timestamp_onboarding_completed",
          "type": "timestamp",
          "primaryKey": false,
          "notNull": false
        },
        "timestamp_updated_at": {
          "name": "timestamp_updated_at",
          "type": "timestamp",
          "primaryKey": false,
          "notNull": true,
          "default": "now()"
        },
        "system_role_id": {
          "name": "system_role_id",
          "type": "uuid",
          "primaryKey": false,
          "notNull": false
        },
        "user_type_id": {
          "name": "user_type_id",
          "type": "uuid",
          "primaryKey": false,
          "notNull": false
        },
        "banned": {
          "name": "banned",
          "type": "boolean",
          "primaryKey": false,
          "notNull": false,
          "default": false
        },
        "ban_reason": {
          "name": "ban_reason",
          "type": "text",
          "primaryKey": false,
          "notNull": false
        },
        "ban_expires": {
          "name": "ban_expires",
          "type": "timestamp",
          "primaryKey": false,
          "notNull": false
        }
      },
      "indexes": {},
      "foreignKeys": {
        "system_role_fkey": {
          "name": "system_role_fkey",
          "tableFrom": "user",
          "tableTo": "system_roles",
          "schemaTo": "authz",
          "columnsFrom": [
            "system_role_id"
          ],
          "columnsTo": [
            "id"
          ],
          "onDelete": "restrict",
          "onUpdate": "no action"
        },
        "user_type_fkey": {
          "name": "user_type_fkey",
          "tableFrom": "user",
          "tableTo": "user_types",
          "schemaTo": "authz",
          "columnsFrom": [
            "user_type_id"
          ],
          "columnsTo": [
            "id"
          ],
          "onDelete": "restrict",
          "onUpdate": "no action"
        }
      },
      "compositePrimaryKeys": {},
      "uniqueConstraints": {
        "user_email_unique": {
          "name": "user_email_unique",
          "nullsNotDistinct": false,
          "columns": [
            "email"
          ]
        }
      },
      "policies": {},
      "checkConstraints": {},
      "isRLSEnabled": false
    },
    "authz.user_types": {
      "name": "user_types",
      "schema": "authz",
      "columns": {
        "id": {
          "name": "id",
          "type": "uuid",
          "primaryKey": true,
          "notNull": true,
          "default": "uuid_generate_v7()"
        },
        "name": {
          "name": "name",
          "type": "text",
          "primaryKey": false,
          "notNull": true
        },
        "display": {
          "name": "display",
          "type": "text",
          "primaryKey": false,
          "notNull": true
        }
      },
      "indexes": {},
      "foreignKeys": {},
      "compositePrimaryKeys": {},
      "uniqueConstraints": {
        "user_types_name_key": {
          "name": "user_types_name_key",
          "nullsNotDistinct": false,
          "columns": [
            "name"
          ]
        }
      },
      "policies": {},
      "checkConstraints": {},
      "isRLSEnabled": false
    },
    "better-auth.verification": {
      "name": "verification",
      "schema": "better-auth",
      "columns": {
        "id": {
          "name": "id",
          "type": "uuid",
          "primaryKey": true,
          "notNull": true,
          "default": "uuid_generate_v7()"
        },
        "identifier": {
          "name": "identifier",
          "type": "text",
          "primaryKey": false,
          "notNull": true
        },
        "value": {
          "name": "value",
          "type": "text",
          "primaryKey": false,
          "notNull": true
        },
        "expires_at": {
          "name": "expires_at",
          "type": "timestamp",
          "primaryKey": false,
          "notNull": true
        },
        "created_at": {
          "name": "created_at",
          "type": "timestamp",
          "primaryKey": false,
          "notNull": true,
          "default": "now()"
        },
        "updated_at": {
          "name": "updated_at",
          "type": "timestamp",
          "primaryKey": false,
          "notNull": true,
          "default": "now()"
        }
      },
      "indexes": {},
      "foreignKeys": {},
      "compositePrimaryKeys": {},
      "uniqueConstraints": {},
      "policies": {},
      "checkConstraints": {},
      "isRLSEnabled": false
    }
  },
  "enums": {
    "public.account_status": {
      "name": "account_status",
      "schema": "public",
      "values": [
        "active",
        "inactive",
        "invited"
      ]
    },
    "public.shift_status": {
      "name": "shift_status",
      "schema": "public",
      "values": [
        "active",
        "deleted"
      ]
    },
    "public.single_multiple": {
      "name": "single_multiple",
      "schema": "public",
      "values": [
        "single",
        "multiple"
      ]
    },
    "public.slot_status": {
      "name": "slot_status",
      "schema": "public",
      "values": [
        "active",
        "deleted"
      ]
    }
  },
  "schemas": {
    "authz": "authz",
    "better-auth": "better-auth",
    "calendar": "calendar"
  },
  "sequences": {},
  "roles": {},
  "policies": {},
  "views": {},
  "_meta": {
    "columns": {},
    "schemas": {},
    "tables": {}
  }
}